dora_piper/__init__.py
dora_piper/main.py
dora_piper-0.4.1.dist-info/METADATA
dora_piper-0.4.1.dist-info/WHEEL
dora_piper-0.4.1.dist-info/entry_points.txt
dora_piper-0.4.1.dist-info/top_level.txt
dora_piper-0.4.1.dist-info/RECORD
