Metadata-Version: 2.4
Name: dora-piper
Version: 0.4.1
Summary: Dora Node for using Agilex piper
Author-email: Haixuan Xavier Tao <tao.xavier@outlook.com>
License: MIT
Requires-Python: >=3.8
Requires-Dist: dora-rs>=0.3.9
Requires-Dist: piper_sdk>=0.0.8
Requires-Dist: numpy<2.0.0
